labphew/__init__.py
labphew/__main__.py
labphew/ad2-sim.py
labphew/blink.py
labphew/controller/__init__.py
labphew/controller/blink_controller.py
labphew/controller/arduino/__init__.py
labphew/controller/arduino/arduino_controller.py
labphew/controller/arduino/simple_daq.py
labphew/controller/basler/__init__.py
labphew/controller/basler/basler_controller.py
labphew/controller/digilent/__init__.py
labphew/controller/digilent/waveforms.py
labphew/core/__init__.py
labphew/core/base/__init__.py
labphew/core/base/camera_base.py
labphew/core/base/general_worker.py
labphew/core/base/operator_base.py
labphew/core/base/tools.py
labphew/core/base/view_base.py
labphew/core/tools/__init__.py
labphew/core/tools/gui_tools.py
labphew/model/__init__.py
labphew/model/analog_discovery_2_model.py
labphew/model/blink_model.py
labphew/model/camera_basler_model.py
labphew/view/__init__.py
labphew/view/analog_discovery_2_view.py
labphew/view/blink_view.py
labphew/view/design/icons/LICENSE.txt
labphew/view/design/icons/arrow_bottom.png
labphew/view/design/icons/arrow_left.png
labphew/view/design/icons/arrow_right.png
labphew/view/design/icons/arrow_top.png
labphew/view/design/icons/avocado_calibrate.svg
labphew/view/design/icons/duotone_chart.svg
labphew/view/design/icons/duotone_edit.svg
labphew/view/design/icons/hatch_ask.svg
labphew/view/design/icons/hatch_download.svg
labphew/view/design/icons/hatch_enlarge.svg
labphew/view/design/icons/labphew_icon.png
labphew/view/design/icons/pictogram_close.svg
labphew/view/design/icons/pictogram_crop.svg
labphew/view/design/icons/pictogram_link.svg
labphew/view/design/icons/pictogram_open.svg
labphew/view/design/icons/pictogram_play.svg
labphew/view/design/icons/pictogram_record.svg
labphew/view/design/icons/pictogram_save.svg
labphew/view/design/icons/science-and-fiction_capture.svg
labphew/view/design/icons/science-and-fiction_upload.svg
labphew/view/design/icons/sketchy_create.svg
labphew-0.3.2.dist-info/LICENSE
labphew-0.3.2.dist-info/METADATA
labphew-0.3.2.dist-info/WHEEL
labphew-0.3.2.dist-info/entry_points.txt
labphew-0.3.2.dist-info/top_level.txt
labphew-0.3.2.dist-info/RECORD
