Metadata-Version: 2.1
Name: labphew
Version: 0.3.2
Summary: Fun with computer-controlled experiments for beginners
Home-page: https://github.com/sanlifaez/labphew
Author: Sanli Faez, Aron Opheij
Author-email: s.faez@uu.nl
License: GPLv3
Platform: UNKNOWN
Classifier: Programming Language :: Python :: 3
Classifier: Programming Language :: Python :: 3.6
Classifier: Programming Language :: Python :: 3.7
Requires-Dist: pint
Requires-Dist: pyqt5 (==5.13.2)
Requires-Dist: pyqtgraph
Requires-Dist: numpy
Requires-Dist: PyYAML
Requires-Dist: pyserial
Requires-Dist: dwf
Requires-Dist: xarray
Requires-Dist: scipy
